clara/chat.py
clara/cli.py
clara/config.py
clara/console.py
clara/consts.py
clara/index.py
clara/utils.py
clara_ai-0.0.10.dist-info/LICENSE
clara_ai-0.0.10.dist-info/METADATA
clara_ai-0.0.10.dist-info/WHEEL
clara_ai-0.0.10.dist-info/entry_points.txt
clara_ai-0.0.10.dist-info/RECORD
