Metadata-Version: 2.1
Name: clara-ai
Version: 0.0.10
Summary: CLARA: Code Language Assistant & Repository Analyzer
Author: Cristóbal Carnero Liñán
Author-email: cristobal@seednapse.ai
Requires-Python: >=3.10,<4.0
Classifier: Programming Language :: Python :: 3
Classifier: Programming Language :: Python :: 3.10
Classifier: Programming Language :: Python :: 3.11
Requires-Dist: chromadb (>=0.3.21,<0.4.0)
Requires-Dist: click (>=8.1.3,<9.0.0)
Requires-Dist: esprima (>=4.0.1,<5.0.0)
Requires-Dist: fire (>=0.5.0,<0.6.0)
Requires-Dist: langchain (>=0.0.139)
Requires-Dist: mergedeep (>=1.3.4,<2.0.0)
Requires-Dist: nbconvert (>=7.3.1,<8.0.0)
Requires-Dist: openai (>=0.27.8,<0.28.0)
Requires-Dist: prompt-toolkit (>=3.0.38,<4.0.0)
Requires-Dist: pyyaml (>=6.0,<7.0)
Requires-Dist: rich (>=13.3.3,<14.0.0)
Requires-Dist: tiktoken (>=0.3.3,<0.4.0)
